cinematicasim/cinematicasim.py
cinematicasim-1.0.1.dist-info/LICENSE.txt
cinematicasim-1.0.1.dist-info/METADATA
cinematicasim-1.0.1.dist-info/WHEEL
cinematicasim-1.0.1.dist-info/top_level.txt
cinematicasim-1.0.1.dist-info/RECORD
